{
	"configurations" : 
	[
		{
			"directories" : 
			[
				{
					"build" : ".",
					"jsonFile" : "directory-.-Debug-d0094a50bb2071803777.json",
					"minimumCMakeVersion" : 
					{
						"string" : "3.26"
					},
					"projectIndex" : 0,
					"source" : ".",
					"targetIndexes" : 
					[
						0
					]
				}
			],
			"name" : "Debug",
			"projects" : 
			[
				{
					"directoryIndexes" : 
					[
						0
					],
					"name" : "apsc142assign4",
					"targetIndexes" : 
					[
						0
					]
				}
			],
			"targets" : 
			[
				{
					"directoryIndex" : 0,
					"id" : "apsc142assign4::@6890427a1f51a3e7e1df",
					"jsonFile" : "target-apsc142assign4-Debug-fa22fe49194afd9d2968.json",
					"name" : "apsc142assign4",
					"projectIndex" : 0
				}
			]
		}
	],
	"kind" : "codemodel",
	"paths" : 
	{
		"build" : "C:/Users/Francesca Adaobi/CLionProjects/apsc142assign4/cmake-build-debug",
		"source" : "C:/Users/Francesca Adaobi/CLionProjects/apsc142assign4"
	},
	"version" : 
	{
		"major" : 2,
		"minor" : 5
	}
}
